easy_agent_sdk-0.1.4.dist-info/licenses/LICENSE
easyagent/__init__.py
easyagent/py.typed
easyagent/agent/__init__.py
easyagent/agent/base.py
easyagent/agent/react_agent.py
easyagent/agent/sandbox_agent.py
easyagent/agent/tool_agent.py
easyagent/config/__init__.py
easyagent/config/base.py
easyagent/config/config_example.yaml
easyagent/debug/__init__.py
easyagent/debug/log.py
easyagent/memory/__init__.py
easyagent/memory/base.py
easyagent/memory/sliding_window.py
easyagent/memory/step_window.py
easyagent/memory/summary.py
easyagent/model/__init__.py
easyagent/model/base.py
easyagent/model/litellm_model.py
easyagent/model/schema.py
easyagent/pipeline/__init__.py
easyagent/pipeline/base.py
easyagent/prompt/__init__.py
easyagent/prompt/memory.py
easyagent/prompt/react.py
easyagent/sandbox/__init__.py
easyagent/sandbox/base.py
easyagent/sandbox/impl/__init__.py
easyagent/sandbox/impl/docker.py
easyagent/sandbox/impl/local.py
easyagent/test/__init__.py
easyagent/test/test_agent.py
easyagent/test/test_log_save.py
easyagent/test/test_model.py
easyagent/test/test_sandbox.py
easyagent/test/test_serper.py
easyagent/tool/__init__.py
easyagent/tool/base.py
easyagent/tool/manager.py
easyagent/tool/code/__init__.py
easyagent/tool/code/bash.py
easyagent/tool/code/file.py
easyagent/tool/web/__init__.py
easyagent/tool/web/serper.py
easy_agent_sdk-0.1.4.dist-info/METADATA
easy_agent_sdk-0.1.4.dist-info/WHEEL
easy_agent_sdk-0.1.4.dist-info/top_level.txt
easy_agent_sdk-0.1.4.dist-info/RECORD
