Metadata-Version: 2.4
Name: easy-agent-sdk
Version: 0.1.4
Summary: A lightweight AI Agent framework built on LiteLLM with ReAct reasoning, tool calling, and smart memory.
Author-email: Yiran Peng <amagipeng@gmail.com>
Maintainer-email: Yiran Peng <amagipeng@gmail.com>
License: MIT
Project-URL: Homepage, https://github.com/SNHuan/EasyAgent
Project-URL: Documentation, https://github.com/SNHuan/EasyAgent#readme
Project-URL: Repository, https://github.com/SNHuan/EasyAgent
Project-URL: Bug Tracker, https://github.com/SNHuan/EasyAgent/issues
Project-URL: Changelog, https://github.com/SNHuan/EasyAgent/releases
Keywords: agent,llm,react,ai,litellm,openai,claude,gpt,tool-calling
Classifier: Development Status :: 3 - Alpha
Classifier: Intended Audience :: Developers
Classifier: License :: OSI Approved :: MIT License
Classifier: Operating System :: OS Independent
Classifier: Programming Language :: Python :: 3
Classifier: Programming Language :: Python :: 3.12
Classifier: Programming Language :: Python :: 3.13
Classifier: Topic :: Scientific/Engineering :: Artificial Intelligence
Classifier: Topic :: Software Development :: Libraries :: Python Modules
Classifier: Typing :: Typed
Requires-Python: >=3.12
License-File: LICENSE
Requires-Dist: litellm>=1.80.0
Requires-Dist: pydantic>=2.12.5
Provides-Extra: dev
Requires-Dist: pytest>=8.0; extra == "dev"
Requires-Dist: pytest-asyncio>=0.23; extra == "dev"
Requires-Dist: build; extra == "dev"
Requires-Dist: twine; extra == "dev"
Provides-Extra: sandbox
Requires-Dist: docker>=7.0; extra == "sandbox"
Provides-Extra: web
Requires-Dist: httpx>=0.27; extra == "web"
Provides-Extra: all
Requires-Dist: easy-agent-sdk[sandbox,web]; extra == "all"
Dynamic: license-file
